composio_tools/__init__.py
composio_tools/lib/__init__.py
composio_tools/lib/action.py
composio_tools/lib/headers.py
composio_tools/lib/tool.py
composio_tools/lib/trigger.py
composio_tools-0.0.3.dist-info/METADATA
composio_tools-0.0.3.dist-info/WHEEL
composio_tools-0.0.3.dist-info/top_level.txt
composio_tools-0.0.3.dist-info/RECORD
