Metadata-Version: 2.1
Name: composio-tools
Version: 0.0.3
Summary: Add tools to Composio using this package
Home-page: https://github.com/SamparkAI/tools
Author: Karan
Author-email: karan@composio.dev
Classifier: Programming Language :: Python :: 3
Classifier: License :: OSI Approved :: Apache Software License
Classifier: Operating System :: OS Independent
Requires-Python: >=3.7
Requires-Dist: pydantic
Requires-Dist: inflection
